pvp_api/__init__.py
pvp_api/generator.py
pvp_api_pe_decomposition/__init__.py
pvp_api_pe_decomposition/pe_decomposition.py
pvp_api_scenario_library/__init__.py
pvp_api_scenario_library/scenario_library.py
pvp_create_project/__init__.py
pvp_backend_api-0.7.dist-info/METADATA
pvp_backend_api-0.7.dist-info/WHEEL
pvp_backend_api-0.7.dist-info/entry_points.txt
pvp_backend_api-0.7.dist-info/top_level.txt
pvp_backend_api-0.7.dist-info/RECORD
