Metadata-Version: 2.1
Name: pvp-backend-api
Version: 0.7
Summary: A Python package to generate a PVP API template
Home-page: https://github.com/yourusername/pvp-api-package
Author: Sachin Raghav
Author-email: sraghav872@gmail.com
License: UNKNOWN
Platform: UNKNOWN
Requires-Dist: click
